{"i":{"CuvGzrUAs":{"id":"CuvGzrUAs","type":"slide","setup":{"bord":{"size":0,"rad":0},"bg":{"selectedKey":"gradient","fill":{"opac":0,"rgb":"#9832b2"},"img":{"filt":{"opac":100,"gray":0,"blur":0,"tint":{"rgb":"var(--TC3)","opac":0.5,"blendMode":"multiply"}},"pos":{"type":"crop","fit":{"bg":{"color":{"rgb":"#FFF","opac":100}},"vali":"center","hali":"center"},"crop":{"poi":{"x":1072,"y":283}}},"measures":{"size":{"width":1080,"height":591}}},"gradient":{"angle":0,"opac":0,"stops":[{"color":"#000000","pos":0},{"color":"#000000","pos":100}]}},"transparentBg":{"selectedKey":false}}},"2zHemOXv4":{"id":"2zHemOXv4","type":"interactive","subtype":"interactiveRichText","setup":{"frmeTp":{"selectedKey":"thinFrame"},"bg":{"selectedKey":"fill","fill":{"opac":0.2,"rgb":"#FFF"}},"txt":{"val":{"ops":[{"insert":"Funciones","attributes":{"color":"var(--TC13)","bold":true}},{"insert":"\n\n\n","attributes":{"align":"center"}},{"insert":"La multiplicación y suma de nuevos individuos a la sociedad. ","attributes":{"color":"var(--TC13)","lang":"ES-CO"}},{"insert":"​","attributes":{"color":"var(--TC13)"}},{"insert":"\n","attributes":{"list":"bullet"}},{"insert":"Desempeño de sus funciones sexuales. ","attributes":{"lang":"ES-CO","color":"var(--TC13)"}},{"insert":"​","attributes":{"color":"var(--TC13)"}},{"insert":"\n","attributes":{"list":"bullet"}},{"insert":"Ampliación de la familia con los hijos y consolidar los roles.","attributes":{"lang":"ES-CO","color":"var(--TC13)"}},{"insert":"​","attributes":{"color":"var(--TC13)"}},{"insert":"\n","attributes":{"list":"bullet"}},{"insert":"Perpetuar la especie humana, consolidación del grupo familiar.","attributes":{"lang":"ES-CO","color":"var(--TC13)"}},{"attributes":{"list":"bullet"},"insert":"\n"},{"insert":"\n\n\n"}]},"rType":"richtext"},"hali":"","paddV1":26,"vali":"middle","frmeColo":{"color":{"opac":1,"rgb":"#7655c0"}}}},"1gsPbJmrq":{"id":"1gsPbJmrq","type":"interactive","subtype":"interactiveRichText","setup":{"frmeTp":{"selectedKey":"thinFrame"},"bg":{"selectedKey":"fill","fill":{"opac":0.05,"rgb":"var(--TC4)"}},"txt":{"val":{"ops":[{"insert":"Concepto","attributes":{"color":"var(--TC13)","bold":true}},{"insert":"\n\n\n","attributes":{"align":"center"}},{"insert":"Se da por la supervivencia de dos individuos de la especie humana, de sexo distinto, unidos, con el fin de reproducir, y por ende de conservar la especie a través del tiempo.","attributes":{"color":"var(--TC13)","lang":"ES-CO"}},{"insert":"\n\n\n\n\n\n","attributes":{"align":"justify"}}]},"rType":"richtext"},"hali":"","paddV1":26,"vali":"middle","frmeColo":{"color":{"opac":1,"rgb":"#7655c0"}}}},"eQtIrB7qe":{"id":"eQtIrB7qe","type":"interactive","subtype":"interactiveRichText","setup":{"frmeTp":{"selectedKey":"bottomLine"},"bg":{"selectedKey":"fill","fill":{"opac":0.2,"rgb":"#FFF"}},"txt":{"val":{"ops":[{"insert":"Conceptos y funciones de la familia","attributes":{"color":"#7655c0","bold":true,"lang":"EN-US","background":"rgba(0, 0, 0, 0)"}},{"insert":"\n","attributes":{"size":"largeTitle","align":"center"}}]},"rType":"richtext"},"vali":"middle","hali":"","frmeColo":{"color":{"opac":1,"rgb":"#7655c0"}}}},"h0R73xjlr":{"id":"h0R73xjlr","type":"interactive","subtype":"interactiveRichText","setup":{"frmeTp":{"selectedKey":"thinFrame"},"bg":{"selectedKey":"fill","fill":{"opac":0.2,"rgb":"#FFF"}},"txt":{"val":{"ops":[{"attributes":{"align":"center"},"insert":"\n"},{"insert":"Tipo","attributes":{"bold":true,"color":"var(--TC13)"}},{"insert":"\n\n\n\n\n","attributes":{"align":"center"}},{"insert":"Biológico","attributes":{"background":"rgba(0, 0, 0, 0)","lang":"ES-CO","color":"var(--TC13)"}},{"insert":"\n\n\n\n\n\n\n\n\n\n","attributes":{"align":"center"}}]},"rType":"richtext"},"hali":"","paddV1":26,"vali":"middle","frmeColo":{"color":{"opac":1,"rgb":"#7655c0"}}}}},"v":"1"}